ciclope/__about__.py
ciclope/__init__.py
ciclope/pipeline.py
ciclope/core/__init__.py
ciclope/core/tetraFE.py
ciclope/core/voxelFE.py
ciclope/utils/__init__.py
ciclope/utils/dat2txt.py
ciclope/utils/postprocess.py
ciclope/utils/preprocess.py
ciclope/utils/recon_utils.py
ciclope/utils/timer.py
ciclope-2.0.0.dist-info/LICENSE
ciclope-2.0.0.dist-info/METADATA
ciclope-2.0.0.dist-info/WHEEL
ciclope-2.0.0.dist-info/entry_points.txt
ciclope-2.0.0.dist-info/top_level.txt
ciclope-2.0.0.dist-info/RECORD
