Metadata-Version: 2.1
Name: ciclope
Version: 2.0.0
Summary: Computed Tomography to Finite Elements
Author: Gigi Crimi
Author-email: Gianluca Iori <gianthk.iori@gmail.com>, Martino Pani <martino.pani@port.ac.uk>, Alfonso Dario Santamaria <dariosantamaria99@gmail.com>
License: MIT License
Project-URL: Home, https://github.com/gianthk/ciclope
Keywords: computed tomography,finite elements,image processing,engineering,simulation,biomechanics
Classifier: License :: OSI Approved :: MIT License
Classifier: Development Status :: 3 - Alpha
Classifier: Intended Audience :: Science/Research
Classifier: Operating System :: OS Independent
Classifier: Programming Language :: Python
Classifier: Programming Language :: Python :: 3
Classifier: Programming Language :: Python :: 3.7
Classifier: Programming Language :: Python :: 3.8
Classifier: Programming Language :: Python :: 3.9
Classifier: Programming Language :: Python :: 3.10
Classifier: Programming Language :: Python :: 3.11
Classifier: Topic :: Scientific/Engineering
Classifier: Topic :: Utilities
Requires-Python: >=3.7
License-File: LICENSE
Requires-Dist: numpy~=1.26
Requires-Dist: meshio==5.0.0
Requires-Dist: pygalmesh>=0.10.6
Requires-Dist: PyMCubes
Requires-Dist: scipy
Requires-Dist: scikit-image
Requires-Dist: pypng
Requires-Dist: tqdm
Requires-Dist: matplotlib
Requires-Dist: tifffile
Requires-Dist: h5py
Requires-Dist: opencv
Provides-Extra: all
Requires-Dist: itkwidgets; extra == "all"
Requires-Dist: itk; extra == "all"
Requires-Dist: vtk; extra == "all"
Requires-Dist: ccx2paraview; extra == "all"
